{
  "HALProvider": {
    "Other Devices": {
      "CANCoder (Pro)[0]": {
        "header": {
          "open": true
        }
      }
    },
    "PWM Outputs": {
      "window": {
        "visible": true
      }
    },
    "RoboRIO": {
      "6V Rail": {
        "open": true
      },
      "RoboRIO Input": {
        "open": true
      }
    }
  },
  "NTProvider": {
    "types": {
      "/FMSInfo": "FMSInfo"
    }
  },
  "NetworkTables": {
    "Retained Values": {
      "open": false
    }
  }
}
